{
  "activities": 991, 
  "activities_no_country": 413, 
  "activities_per_country": {
    "AF": 1, 
    "BD": 14, 
    "BI": 5, 
    "BJ": 1, 
    "BO": 10, 
    "BR": 13, 
    "CD": 61, 
    "CL": 1, 
    "CO": 8, 
    "ER": 1, 
    "GT": 8, 
    "HN": 4, 
    "HT": 21, 
    "ID": 14, 
    "IL": 2, 
    "JO": 1, 
    "KE": 49, 
    "KG": 1, 
    "KH": 3, 
    "LB": 3, 
    "LK": 7, 
    "LR": 9, 
    "ML": 1, 
    "MM": 1, 
    "MR": 1, 
    "MW": 5, 
    "MX": 1, 
    "MZ": 42, 
    "NE": 19, 
    "NG": 16, 
    "NI": 7, 
    "PE": 8, 
    "PH": 12, 
    "PK": 13, 
    "PS": 3, 
    "RW": 14, 
    "SD": 18, 
    "SL": 16, 
    "SS": 31, 
    "SV": 3, 
    "SZ": 1, 
    "TD": 1, 
    "TH": 1, 
    "TL": 8, 
    "TZ": 3, 
    "UG": 5, 
    "ZM": 21, 
    "ZW": 90
  }, 
  "activities_per_year": {
    "1983": 2, 
    "1985": 1, 
    "1986": 2, 
    "1988": 2, 
    "1989": 1, 
    "1990": 3, 
    "1991": 1, 
    "1992": 1, 
    "1993": 2, 
    "1994": 1, 
    "1995": 1, 
    "1996": 1, 
    "1997": 4, 
    "1998": 5, 
    "1999": 3, 
    "2000": 7, 
    "2001": 9, 
    "2002": 6, 
    "2003": 14, 
    "2004": 25, 
    "2005": 16, 
    "2006": 17, 
    "2007": 49, 
    "2008": 68, 
    "2009": 84, 
    "2010": 168, 
    "2011": 168, 
    "2012": 153, 
    "2013": 117, 
    "null": 60
  }, 
  "currencies": {
    "GBP": 931
  }, 
  "iati_identifier": null, 
  "publishers": 1, 
  "publishers_per_country": {
    "AF": 1, 
    "BD": 1, 
    "BI": 1, 
    "BJ": 1, 
    "BO": 1, 
    "BR": 1, 
    "CD": 1, 
    "CL": 1, 
    "CO": 1, 
    "ER": 1, 
    "GT": 1, 
    "HN": 1, 
    "HT": 1, 
    "ID": 1, 
    "IL": 1, 
    "JO": 1, 
    "KE": 1, 
    "KG": 1, 
    "KH": 1, 
    "LB": 1, 
    "LK": 1, 
    "LR": 1, 
    "ML": 1, 
    "MM": 1, 
    "MR": 1, 
    "MW": 1, 
    "MX": 1, 
    "MZ": 1, 
    "NE": 1, 
    "NG": 1, 
    "NI": 1, 
    "PE": 1, 
    "PH": 1, 
    "PK": 1, 
    "PS": 1, 
    "RW": 1, 
    "SD": 1, 
    "SL": 1, 
    "SS": 1, 
    "SV": 1, 
    "SZ": 1, 
    "TD": 1, 
    "TH": 1, 
    "TL": 1, 
    "TZ": 1, 
    "UG": 1, 
    "ZM": 1, 
    "ZW": 1
  }, 
  "publishers_per_organisation_type": {
    "21": 1
  }, 
  "spend": 82506769.5198, 
  "spend_per_country": {
    "289": 59936.1108, 
    "298": 147371.6283, 
    "389": 114697.7391, 
    "489": 91539.2029, 
    "589": 26506.2, 
    "798": 77001.65, 
    "AF": 32375.0, 
    "BD": 232808.4253, 
    "BI": 155244.6442, 
    "BJ": 28152.005, 
    "BO": 257492.2785, 
    "BR": 687647.4655, 
    "CD": 1941677.6147, 
    "CL": 32375.0, 
    "CO": 217526.7689, 
    "ER": 74515.2392, 
    "GT": 325464.7481, 
    "HN": 148867.3851, 
    "HT": 4920682.6806, 
    "ID": 501851.932, 
    "IL": 63230.0, 
    "JO": 29146.7224, 
    "KE": 3978842.0052, 
    "KG": 16229.5875, 
    "KH": 47047.7366, 
    "LB": 260965.7097, 
    "LK": 413444.0684, 
    "LR": 503457.3566, 
    "ML": 12261.6419, 
    "MM": 9239.9351, 
    "MR": 38068.5831, 
    "MW": 232206.635, 
    "MX": 22082.189, 
    "MZ": 1804783.7213, 
    "NE": 790969.1467, 
    "NG": 590846.9691, 
    "NI": 214806.3284, 
    "PE": 197252.3111, 
    "PH": 275266.75, 
    "PK": 2005437.8439, 
    "PS": 171724.6459, 
    "RW": 261267.12, 
    "SD": 3726534.0056, 
    "SL": 335149.1811, 
    "SS": 3903676.8292, 
    "SV": 68718.4253, 
    "SZ": 54234.2096, 
    "TD": 12419.4169, 
    "TH": 9933.3912, 
    "TL": 271374.3218, 
    "TZ": 206461.0026, 
    "UG": 78354.4229, 
    "ZM": 1113693.0422, 
    "ZW": 7236757.5731, 
    "pre2010": 43477152.9732
  }, 
  "spend_per_organisation_type": {
    "21": 10652013.1457
  }, 
  "spend_per_year": {
    "1983": 812908.9053, 
    "1985": 232514.6454, 
    "1986": 555826.0387, 
    "1988": 718747.7007, 
    "1989": 124104.6228, 
    "1990": 709906.4456, 
    "1991": 221556.9762, 
    "1992": 235301.7999, 
    "1993": 804822.9052, 
    "1994": 218532.5464, 
    "1995": 301960.4196, 
    "1996": 234302.4673, 
    "1997": 1000075.5199, 
    "1998": 1213207.2876, 
    "1999": 537969.307, 
    "2000": 1338294.9345, 
    "2001": 1574665.3501, 
    "2002": 1137624.1879, 
    "2003": 2124128.3753, 
    "2004": 3136920.265, 
    "2005": 1572648.7918, 
    "2006": 1818061.9819, 
    "2007": 7179272.0399, 
    "2008": 9321738.502, 
    "2009": 6352060.9572, 
    "2010": 13294759.2946, 
    "2011": 15070465.7109, 
    "2012": 6515075.0204, 
    "2013": 4149316.5207, 
    "null": 0
  }
}