{
  "activities": 188529, 
  "activities_no_country": 107144, 
  "activities_per_country": {
    "": 1491, 
    "-1": 3, 
    "AA": 12, 
    "AE": 1, 
    "AF": 2964, 
    "AG": 8, 
    "AI": 13, 
    "AL": 305, 
    "AM": 635, 
    "AO": 490, 
    "AP": 9, 
    "AR": 150, 
    "AU": 15, 
    "AY": 6, 
    "AZ": 434, 
    "BA": 433, 
    "BB": 13, 
    "BD": 1332, 
    "BE": 4, 
    "BF": 456, 
    "BG": 10, 
    "BI": 393, 
    "BJ": 561, 
    "BL": 3, 
    "BM": 1, 
    "BO": 486, 
    "BR": 474, 
    "BS": 3, 
    "BT": 22, 
    "BU": 15, 
    "BW": 201, 
    "BY": 150, 
    "BZ": 49, 
    "CA": 21, 
    "CB": 2, 
    "CD": 896, 
    "CE": 21, 
    "CF": 128, 
    "CG": 122, 
    "CH": 9, 
    "CI": 198, 
    "CK": 22, 
    "CL": 295, 
    "CM": 232, 
    "CN": 837, 
    "CO": 834, 
    "CR": 251, 
    "CU": 166, 
    "CV": 200, 
    "CY": 4, 
    "DE": 1, 
    "DJ": 127, 
    "DM": 12, 
    "DO": 539, 
    "DZ": 250, 
    "EA": 3, 
    "EB": 1, 
    "EC": 781, 
    "EG": 809, 
    "EI": 5, 
    "ER": 34, 
    "ES": 2, 
    "ET": 2903, 
    "FJ": 49, 
    "FM": 12, 
    "FR": 4, 
    "GA": 37, 
    "GB": 74, 
    "GD": 4, 
    "GE": 1080, 
    "GH": 1089, 
    "GM": 61, 
    "GN": 315, 
    "GQ": 6, 
    "GR": 2, 
    "GT": 1234, 
    "GW": 39, 
    "GY": 214, 
    "HK": 1, 
    "HN": 791, 
    "HR": 41, 
    "HT": 1771, 
    "HU": 2, 
    "ID": 2460, 
    "IE": 5, 
    "IL": 18, 
    "IM": 2, 
    "IN": 2060, 
    "IQ": 870, 
    "IR": 43, 
    "IT": 1, 
    "JM": 472, 
    "JO": 1070, 
    "JP": 42, 
    "KE": 2881, 
    "KG": 719, 
    "KH": 908, 
    "KI": 17, 
    "KM": 46, 
    "KN": 9, 
    "KO": 31, 
    "KP": 57, 
    "KR": 8, 
    "KS": 36, 
    "KZ": 773, 
    "LA": 142, 
    "LB": 331, 
    "LC": 13, 
    "LE": 8, 
    "LK": 779, 
    "LR": 952, 
    "LS": 636, 
    "LT": 8, 
    "LY": 54, 
    "MA": 785, 
    "MB": 27, 
    "MD": 435, 
    "ME": 210, 
    "MG": 430, 
    "MH": 17, 
    "MK": 353, 
    "ML": 1581, 
    "MM": 360, 
    "MN": 633, 
    "MR": 138, 
    "MS": 11, 
    "MU": 56, 
    "MV": 18, 
    "MW": 969, 
    "MX": 960, 
    "MY": 90, 
    "MZ": 1551, 
    "NA": 727, 
    "NB": 15, 
    "NE": 441, 
    "NES": 93, 
    "NG": 1981, 
    "NI": 864, 
    "NL": 42, 
    "NO": 8, 
    "NP": 1184, 
    "NR": 6, 
    "NS": 84, 
    "NU": 4, 
    "NZ": 2, 
    "OM": 12, 
    "OT": 2, 
    "PA": 233, 
    "PE": 804, 
    "PG": 112, 
    "PH": 1706, 
    "PK": 2897, 
    "PL": 4, 
    "PR": 3, 
    "PS": 915, 
    "PW": 10, 
    "PY": 463, 
    "QA": 1, 
    "RO": 11, 
    "RS": 661, 
    "RU": 213, 
    "RW": 863, 
    "SB": 35, 
    "SC": 34, 
    "SD": 1223, 
    "SE": 1, 
    "SG": 1, 
    "SH": 13, 
    "SK": 7, 
    "SL": 338, 
    "SN": 1052, 
    "SO": 503, 
    "SP": 63, 
    "SQ": 42, 
    "SR": 13, 
    "SS": 387, 
    "ST": 13, 
    "SV": 567, 
    "SW": 2, 
    "SX": 10, 
    "SY": 82, 
    "SZ": 68, 
    "TD": 380, 
    "TG": 27, 
    "TH": 165, 
    "TJ": 113, 
    "TK": 14, 
    "TL": 43, 
    "TM": 332, 
    "TMA": 13, 
    "TN": 222, 
    "TO": 15, 
    "TP": 6, 
    "TR": 134, 
    "TT": 5, 
    "TV": 13, 
    "TW": 6, 
    "TZ": 846, 
    "UA": 738, 
    "UG": 884, 
    "US": 673, 
    "UY": 53, 
    "UZ": 413, 
    "VC": 15, 
    "VE": 142, 
    "VG": 1, 
    "VI": 5, 
    "VN": 943, 
    "VU": 79, 
    "WB": 64, 
    "WS": 24, 
    "XK": 453, 
    "YE": 551, 
    "ZA": 1527, 
    "ZM": 1104, 
    "ZW": 1139, 
    "sv": 3
  }, 
  "activities_per_year": {
    "1": 30354, 
    "1905": 7, 
    "1983": 2, 
    "1985": 1, 
    "1986": 2, 
    "1988": 2, 
    "1989": 1, 
    "1990": 3, 
    "1991": 2, 
    "1992": 1, 
    "1993": 3, 
    "1994": 20, 
    "1995": 45, 
    "1996": 14, 
    "1997": 16, 
    "1998": 15, 
    "1999": 30, 
    "2000": 38, 
    "2001": 134, 
    "2002": 293, 
    "2003": 681, 
    "2004": 968, 
    "2005": 1282, 
    "2006": 2437, 
    "2007": 3413, 
    "2008": 4410, 
    "2009": 38549, 
    "2010": 62988, 
    "2011": 11711, 
    "2012": 12066, 
    "2013": 3742, 
    "2014": 23, 
    "2015": 1, 
    "null": 15275
  }, 
  "currencies": {
    "AUD": 1077, 
    "CHF": 2, 
    "EUR": 7657, 
    "Eur": 1569, 
    "GBP": 13287, 
    "INR": 3, 
    "LSL": 1, 
    "MWK": 1, 
    "NOK": 96, 
    "NPR": 2, 
    "NZD": 69, 
    "SEK": 1, 
    "SLL": 1, 
    "TZS": 1, 
    "UGX": 1, 
    "USD": 158906, 
    "ZAR": 2, 
    "ZMK": 2
  }, 
  "iati_identifier": null, 
  "publishers": 90, 
  "publishers_per_country": {
    "": 3, 
    "-1": 1, 
    "AA": 1, 
    "AE": 1, 
    "AF": 12, 
    "AG": 3, 
    "AI": 3, 
    "AL": 7, 
    "AM": 10, 
    "AO": 9, 
    "AP": 1, 
    "AR": 10, 
    "AU": 1, 
    "AY": 1, 
    "AZ": 9, 
    "BA": 7, 
    "BB": 5, 
    "BD": 14, 
    "BE": 2, 
    "BF": 11, 
    "BG": 3, 
    "BI": 14, 
    "BJ": 9, 
    "BL": 1, 
    "BM": 1, 
    "BO": 13, 
    "BR": 10, 
    "BS": 2, 
    "BT": 9, 
    "BU": 1, 
    "BW": 7, 
    "BY": 9, 
    "BZ": 7, 
    "CA": 1, 
    "CB": 1, 
    "CD": 20, 
    "CE": 1, 
    "CF": 8, 
    "CG": 9, 
    "CH": 4, 
    "CI": 10, 
    "CK": 5, 
    "CL": 9, 
    "CM": 9, 
    "CN": 9, 
    "CO": 11, 
    "CR": 7, 
    "CU": 7, 
    "CV": 7, 
    "CY": 2, 
    "DE": 1, 
    "DJ": 5, 
    "DM": 6, 
    "DO": 8, 
    "DZ": 9, 
    "EA": 1, 
    "EB": 1, 
    "EC": 13, 
    "EG": 9, 
    "EI": 1, 
    "ER": 6, 
    "ES": 1, 
    "ET": 18, 
    "FJ": 7, 
    "FM": 3, 
    "FR": 1, 
    "GA": 3, 
    "GB": 12, 
    "GD": 3, 
    "GE": 9, 
    "GH": 13, 
    "GM": 6, 
    "GN": 8, 
    "GQ": 1, 
    "GR": 1, 
    "GT": 12, 
    "GW": 7, 
    "GY": 5, 
    "HK": 1, 
    "HN": 10, 
    "HR": 4, 
    "HT": 11, 
    "HU": 1, 
    "ID": 15, 
    "IE": 1, 
    "IL": 3, 
    "IM": 1, 
    "IN": 21, 
    "IQ": 10, 
    "IR": 10, 
    "IT": 1, 
    "JM": 7, 
    "JO": 9, 
    "JP": 2, 
    "KE": 24, 
    "KG": 12, 
    "KH": 13, 
    "KI": 5, 
    "KM": 5, 
    "KN": 4, 
    "KO": 1, 
    "KP": 6, 
    "KR": 2, 
    "KS": 2, 
    "KZ": 8, 
    "LA": 10, 
    "LB": 12, 
    "LC": 4, 
    "LE": 1, 
    "LK": 16, 
    "LR": 16, 
    "LS": 10, 
    "LT": 1, 
    "LY": 7, 
    "MA": 7, 
    "MB": 1, 
    "MD": 8, 
    "ME": 6, 
    "MG": 10, 
    "MH": 3, 
    "MK": 7, 
    "ML": 14, 
    "MM": 12, 
    "MN": 9, 
    "MR": 9, 
    "MS": 3, 
    "MU": 5, 
    "MV": 5, 
    "MW": 15, 
    "MX": 11, 
    "MY": 7, 
    "MZ": 14, 
    "NA": 9, 
    "NB": 1, 
    "NE": 10, 
    "NES": 1, 
    "NG": 16, 
    "NI": 13, 
    "NL": 2, 
    "NO": 1, 
    "NP": 20, 
    "NR": 2, 
    "NS": 1, 
    "NU": 1, 
    "NZ": 1, 
    "OM": 2, 
    "OT": 1, 
    "PA": 9, 
    "PE": 17, 
    "PG": 11, 
    "PH": 14, 
    "PK": 17, 
    "PL": 2, 
    "PR": 1, 
    "PS": 11, 
    "PW": 3, 
    "PY": 10, 
    "QA": 1, 
    "RO": 3, 
    "RS": 8, 
    "RU": 3, 
    "RW": 17, 
    "SB": 7, 
    "SC": 6, 
    "SD": 16, 
    "SE": 1, 
    "SG": 1, 
    "SH": 1, 
    "SK": 4, 
    "SL": 13, 
    "SN": 10, 
    "SO": 13, 
    "SP": 1, 
    "SQ": 1, 
    "SR": 3, 
    "SS": 14, 
    "ST": 3, 
    "SV": 11, 
    "SW": 1, 
    "SX": 1, 
    "SY": 10, 
    "SZ": 7, 
    "TD": 12, 
    "TG": 5, 
    "TH": 11, 
    "TJ": 10, 
    "TK": 2, 
    "TL": 8, 
    "TM": 5, 
    "TMA": 1, 
    "TN": 10, 
    "TO": 3, 
    "TP": 1, 
    "TR": 6, 
    "TT": 4, 
    "TV": 3, 
    "TW": 1, 
    "TZ": 20, 
    "UA": 9, 
    "UG": 24, 
    "US": 1, 
    "UY": 7, 
    "UZ": 7, 
    "VC": 5, 
    "VE": 8, 
    "VG": 1, 
    "VI": 1, 
    "VN": 12, 
    "VU": 8, 
    "WB": 1, 
    "WS": 5, 
    "XK": 3, 
    "YE": 12, 
    "ZA": 11, 
    "ZM": 14, 
    "ZW": 18, 
    "sv": 1
  }, 
  "publishers_per_organisation_type": {
    "10": 10, 
    "21": 56, 
    "22": 6, 
    "23": 3, 
    "30": 1, 
    "40": 5, 
    "60": 2, 
    "80": 2, 
    "Government": 1
  }, 
  "spend": 586859722143.5669, 
  "spend_per_country": {
    "-1": 0, 
    "189": 403233.47, 
    "289": 10873335050.2417, 
    "298": 55455096.1133, 
    "380": 23046693.0, 
    "389": 105591516.5623, 
    "489": 269699510.9049, 
    "498": 73975594994.7752, 
    "57": 1313898.0, 
    "589": 50642939.5644, 
    "619": 22310698.8138, 
    "679": 33889540.7112, 
    "689": 5039298.0, 
    "789": 39552748.7365, 
    "798": 30575518732.9108, 
    "88": 0, 
    "889": 51137117.0, 
    "89": 396940887.2025, 
    "998": 33865815637.5699, 
    "AA": 291394.732462, 
    "AE": 2835.0, 
    "AF": 3748561250.117396, 
    "AG": 5557912.0, 
    "AI": 520767.067538, 
    "AL": 37734709.193925, 
    "AM": 208048783.496968, 
    "AO": 117915927.82076, 
    "AP": 327658.953354, 
    "AR": -1890766885.175169, 
    "AU": 104537.0, 
    "AY": 35525.335144, 
    "AZ": 55605447.571555, 
    "BA": 36610491.80162, 
    "BB": 1724218580.0, 
    "BD": 502915880.648411, 
    "BE": 779478.0, 
    "BF": 311730700.7896, 
    "BG": 591138.0, 
    "BI": 99626507.168334, 
    "BJ": 159255211.5166, 
    "BL": 20228.0172, 
    "BO": 139895289.970258, 
    "BR": 9087571015.416357, 
    "BS": 77094.0, 
    "BT": 2603690.188306, 
    "BU": 63547.252071, 
    "BW": 89545054.372919, 
    "BY": 37113725.090545, 
    "BZ": -1499524.089676, 
    "CA": 112065.0, 
    "CB": 28597.267807, 
    "CD": 704440250.808525, 
    "CE": 108511.564268, 
    "CF": 45720768.6265, 
    "CG": 9915981.015018, 
    "CH": 110825122.5103, 
    "CI": 92835176.292356, 
    "CK": 38579576.2718, 
    "CL": 4564917902.375881, 
    "CM": 79900827.006605, 
    "CN": 11543619468.561525, 
    "CO": 871847070.223847, 
    "CR": -40629666.928234, 
    "CU": 24360234.058442, 
    "CV": 63798506.808948, 
    "CY": 0.0, 
    "DE": 235.0, 
    "DJ": 17450545.794, 
    "DM": 6609592.71638, 
    "DO": 429164541.634142, 
    "DZ": 283407704.621588, 
    "EA": 6702.819632, 
    "EB": 4401.570228, 
    "EC": 144091011.178126, 
    "EG": 2730247971.168742, 
    "EI": 72743.831856, 
    "ER": 5785584.4406, 
    "ES": 9092.0, 
    "ET": 1386625882.405643, 
    "FJ": 9631912.91816, 
    "FM": 108145966.0, 
    "FR": 10397.0, 
    "GA": 268476468.0, 
    "GB": 21322344.0277, 
    "GD": 37855.9224, 
    "GE": 402097082.210848, 
    "GH": 713021896.847048, 
    "GM": 14609824.216172, 
    "GN": 36848230.171658, 
    "GQ": 20126892.0, 
    "GR": 750.0, 
    "GT": 287785850.925038, 
    "GW": 8948491.153466, 
    "GY": 29595062.676151, 
    "HK": 520.0, 
    "HN": 335146532.759151, 
    "HR": -68643512.0, 
    "HT": 1336097257.658002, 
    "HU": 7540.0, 
    "ID": 186818435.021755, 
    "IE": 88682.0, 
    "IL": 313912.0, 
    "IM": 35779.5834, 
    "IN": 6472323548.24729, 
    "IQ": 1769423031.80093, 
    "IR": 7952721.985942, 
    "IT": 108256.0, 
    "JM": -6655902.801356, 
    "JO": 651308031.999614, 
    "JP": 10465981.0, 
    "KE": 1026810522.426258, 
    "KG": 62211359.308308, 
    "KH": 169388795.5164, 
    "KI": 11942502.2852, 
    "KM": 1853080.1994, 
    "KN": 35405.730342, 
    "KO": 1018523.830628, 
    "KP": 13126671.489227, 
    "KR": 110520.0, 
    "KS": 135439.958418, 
    "KZ": 2024119694.940975, 
    "LA": 46585746.5661, 
    "LB": 200677476.594589, 
    "LC": 169438.052909, 
    "LE": 149444.242252, 
    "LK": 129350650.497099, 
    "LR": 297899304.7709, 
    "LS": 291630966.25964, 
    "LT": 28946.0, 
    "LY": 44537106.765439, 
    "MA": 537500866.437794, 
    "MB": 307101.027025, 
    "MD": 89263143.245491, 
    "ME": 12188117.474322, 
    "MG": 132723868.916724, 
    "MH": 68799892.016856, 
    "MK": 22072832.843223, 
    "ML": 699900552.549248, 
    "MM": 198793574.942074, 
    "MN": 248415949.711782, 
    "MR": 28490296.209794, 
    "MS": 366684.792868, 
    "MU": 1980374278.683458, 
    "MV": 1770374.91011, 
    "MW": 240910768.454613, 
    "MX": 2192491224.072714, 
    "MY": 3884297323.438019, 
    "MZ": 776212382.497987, 
    "NA": 275995789.314742, 
    "NB": 1422284.971153, 
    "NE": 290114226.6517, 
    "NES": 0.0, 
    "NG": 878395414.603456, 
    "NI": 115756920.351703, 
    "NL": 2723102.622, 
    "NO": 68066352.6543, 
    "NP": 117142126.00348, 
    "NR": 281661.5882, 
    "NS": 4897375.701482, 
    "NU": 1326172.6998, 
    "NZ": 45354.0, 
    "OM": 2906050.0, 
    "OT": 12809.165327, 
    "PA": -824649296.817498, 
    "PE": 2407445577.114218, 
    "PG": 349647440.71614, 
    "PH": 1456213543.255585, 
    "PK": 1986430314.209656, 
    "PL": 4680.0, 
    "PR": 2655.0, 
    "PS": 1369919594.7845, 
    "PW": 19317857.0738, 
    "PY": 34300431.008516, 
    "QA": 60.0, 
    "RO": 359247.7795, 
    "RS": 90079955.87263, 
    "RU": 21406598.0, 
    "RW": 257999352.628335, 
    "SB": 26313411.69286, 
    "SC": 2997614.808528, 
    "SD": 1070557723.490728, 
    "SE": 12145.0, 
    "SG": 35.0, 
    "SH": 511630.724647, 
    "SK": 91070.7901, 
    "SL": 54045567.840833, 
    "SN": 226924301.939314, 
    "SO": 413282674.831159, 
    "SP": 1105268.689472, 
    "SQ": 441533.130848, 
    "SR": 1315075.2958, 
    "SS": 1051935515.83838, 
    "ST": 632184.052, 
    "SV": 820969232.976462, 
    "SW": 36576.044207, 
    "SX": 43430.68731, 
    "SY": 141593844.42444, 
    "SZ": 13910459.361566, 
    "TD": 229112830.824643, 
    "TG": 7543533.113558, 
    "TH": 31892905.686675, 
    "TJ": 16160083.705805, 
    "TK": 68025944.676, 
    "TL": 13887542.588, 
    "TM": 11731909.051203, 
    "TMA": 57960.408462, 
    "TN": 34539380.708939, 
    "TO": 8203900.964818, 
    "TP": 82608.686063, 
    "TR": 5643611.124238, 
    "TT": 150354.0, 
    "TV": 7294330.0514, 
    "TW": 19719.0, 
    "TZ": 683358737.343602, 
    "UA": 304656906.214392, 
    "UG": 198075738.046166, 
    "US": 5549770.0, 
    "UY": 218489338.805632, 
    "UZ": 29200457.783443, 
    "VC": 824139.945047, 
    "VE": -133584603.006012, 
    "VI": 11618.0, 
    "VN": 324844459.856754, 
    "VU": 46431855.10787, 
    "WB": 3825611.950208, 
    "WS": 9920243.268, 
    "XK": 129935295.3626, 
    "YE": 294509787.668932, 
    "ZA": 1362481159.882046, 
    "ZM": 340166297.114515, 
    "ZW": 319429091.880548, 
    "null": 415120660.3986, 
    "pre2010": 353131528220.37726, 
    "sv": 5162.947057
  }, 
  "spend_per_organisation_type": {
    "10": 72017163615.97713, 
    "21": 1036257332.893717, 
    "22": 80857893.6706, 
    "23": 0, 
    "30": 29695.1483, 
    "40": 134192737883.818, 
    "60": 0, 
    "80": 111349.3907, 
    "Government": 3063304397.278
  }, 
  "spend_per_year": {
    "1": 55867022282.0, 
    "1905": 1698349.0, 
    "1983": 812908.9053, 
    "1985": 232514.6454, 
    "1986": 555826.0387, 
    "1988": 718747.7007, 
    "1989": 124104.6228, 
    "1990": 709906.4456, 
    "1991": 393266.9762, 
    "1992": 235301.7999, 
    "1993": 1504273.9052, 
    "1994": 55352440.5066, 
    "1995": 20069771.8669, 
    "1996": 8606976.4673, 
    "1997": 48524868.291, 
    "1998": 1685856.2876, 
    "1999": 10583087.307, 
    "2000": 71834011.5772, 
    "2001": 264533575.6362, 
    "2002": 2372519090.7686, 
    "2003": 747575248.9161, 
    "2004": 872351308.455, 
    "2005": 1449033194.063, 
    "2006": 4539706045.276, 
    "2007": 5282895104.9175, 
    "2008": 5618689413.5538, 
    "2009": 121912347262.91786, 
    "2010": 219931414294.82062, 
    "2011": 5989928776.63915, 
    "2012": 6530838691.328254, 
    "2013": 1276012160.401612, 
    "2014": 0.0, 
    "2015": 0, 
    "null": 153981213481.5298
  }, 
  "versions": {
    " 1.0": 41, 
    "1": 27, 
    "1.0": 402, 
    "1.00": 207, 
    "1.01": 259, 
    "1.02": 264, 
    "1.03": 1, 
    "3.1": 77, 
    "null": 28
  }
}